[
    {
        "title": "Jobrium",
        "about": "Jobrium is an application analytics platform that enables job seekers to keep track of their applications, view their application histories and set application goals.",
        "image": "/jobrium.png",
        "video": null,
        "type": {
            "title": "Software Dev",
            "color": "bg-red-600"
        },
        "svg": [
            "SiTypescript",
            "SiReact",
            "SiNextdotjs",
            "SiNodedotjs",
            "SiGraphql",
            "SiAmazonaws",
            "SiPostgresql"
        ],
        "blog": "/projects/jobrium",
        "live": "https://jobrium.com",
        "github": null
    },
    {
        "title": "upBeet",
        "about": "Recipe tracking app for home cooks. Users can create new recipes simply by pasting an image of the recipe.",
        "image": null,
        "video": "/upBeet-walkthrough-cut.mp4",
        "type": {
            "title": "Software Dev",
            "color": "bg-red-600"
        },
        "svg": [
            "SiTypescript",
            "SiReact",
            "SiNextdotjs",
            "SiNodedotjs",
            "SiApollographql",
            "SiGraphql",
            "SiMysql"
        ],
        "blog": null,
        "github": null,
        "live": null
    },
    {
        "title": "TS-Chat",
        "about": "TS-Chat is a real-time chat platform. Users can create an account, subscribe to specific topics, and send and receive messages in real-time.",
        "image": null,
        "video": null,
        "type": {
            "title": "Software Dev",
            "color": "bg-red-600"
        },
        "svg": [
            "SiTypescript",
            "SiReact",
            "SiStyledcomponents",
            "SiNextdotjs",
            "SiNodedotjs",
            "SiApollographql",
            "SiGraphql",
            "SiPostgresql"
        ],
        "github": "https://github.com/lockedNLevered/ts-chat-server",
        "live": null,
        "blog": null
    },
    {
        "title": "Friends of Japan",
        "about": "Friends of Japan was a social media and content discovery platform focued on Japanese animation and pop-culture.",
        "image": null,
        "video": null,
        "type": {
            "title": "Software Dev",
            "color": "bg-red-600"
        },
        "svg": [
            "SiTypescript",
            "SiReact",
            "SiNextdotjs",
            "SiPython",
            "SiDjango",
            "SiPostgresql",
            "SiAmazonaws"
            
        ],
        "blog": "/projects/friendsofjapan",
        "live": null,
        "github": null
    },
    {
        "title": "Slack Queue",
        "about": "An application to automatically manage a queue in a Slack Workspace.",
        "image": null,
        "video": null,
        "type": {
            "title": "Software Dev",
            "color": "bg-red-600"
        },
        "svg": [
            "SiTypescript",
            "SiRedis",
            "SiDocker"
        ],
        "github": "https://github.com/lockedNLevered/slack-queue",
        "live": null,
        "blog": null
    },
    {
        "title": "Web Assembly Blockchain",
        "about": "A Web Assembly Blockchain served over Node.js to a React client",
        "image": null,
        "video": null,
        "type": {
            "title": "Blockchain",
            "color": "bg-green-600"
        },
        "svg": [
            "SiRust",
            "SiWebassembly",
            "SiTypescript",
            "SiNodedotjs",
            "SiReact"
        ],
        "github": "https://github.com/lockedNLevered/rusty-chain",
        "live": null,
        "blog": null
    },
    {
        "title": "Predicting Credit Default",
        "about": "A machine learning model attempting to predict the likelihood of default by a prospective credit customer.",
        "image": null,
        "video": null,
        "type": {
            "title": "Machine Learning",
            "color": "bg-blue-500"
        },
        "svg": [
            "SiPython",
            "SiJupyter",
            "SiScikitlearn",
            "SiPandas"
        ],
        "github": "https://github.com/lockedNLevered/PredictingCreditDefaultML",
        "live": null,
        "blog": null
    },
    {
        "title": "Investigating the Efficient Market Hypothesis",
        "about": "Academic paper and machine learning model investigating the validity of the Efficient Market Hypothesis as it applies to  three companies stock.",
        "image": null,
        "video": null,
        "type": {
            "title": "Machine Learning",
            "color": "bg-blue-500"
        },
        "svg": [
            "SiPython",
            "SiJupyter",
            "SiTensorflow",
            "SiScikitlearn",
            "SiPandas"
        ],
        "github": "https://github.com/lockedNLevered/EfficientMarketTestML",
        "live": null,
        "blog": null
    }
]